v2sub/__init__.py
v2sub/command.py
v2sub/config.py
v2sub/subscribe.py
v2sub/systemd.py
v2sub/utils.py
v2sub-1.3.dist-info/LICENSE
v2sub-1.3.dist-info/METADATA
v2sub-1.3.dist-info/WHEEL
v2sub-1.3.dist-info/entry_points.txt
v2sub-1.3.dist-info/top_level.txt
v2sub-1.3.dist-info/RECORD
