Metadata-Version: 2.1
Name: v2sub
Version: 1.3
Summary: A v2ray subscriber written in python3
Home-page: https://github.com/airborne007/v2sub
Author: airborne007
Author-email: isrfhltc@outlook.com
License: MIT
Project-URL: Tracker, https://github.com/airborne007/v2sub/issues
Keywords: v2ray,subscriber,linux
Classifier: Programming Language :: Python :: 3
Classifier: Programming Language :: Python :: 3.5
Classifier: Programming Language :: Python :: 3.6
Classifier: Programming Language :: Python :: 3.7
Classifier: Programming Language :: Python :: 3.8
Classifier: Programming Language :: Python :: Implementation :: CPython
Classifier: License :: OSI Approved :: MIT License
Classifier: Operating System :: POSIX :: Linux
Requires-Python: >=3
License-File: LICENSE
Requires-Dist: click (>=7.0)
Requires-Dist: simple-term-menu (>=1.2.1)
